odoo/addons/account_move_name_sequence/README.rst
odoo/addons/account_move_name_sequence/__init__.py
odoo/addons/account_move_name_sequence/__manifest__.py
odoo/addons/account_move_name_sequence/hooks.py
odoo/addons/account_move_name_sequence/demo/account_journal_demo.xml
odoo/addons/account_move_name_sequence/demo/ir_sequence_demo.xml
odoo/addons/account_move_name_sequence/i18n/account_move_name_sequence.pot
odoo/addons/account_move_name_sequence/i18n/ar.po
odoo/addons/account_move_name_sequence/i18n/es.po
odoo/addons/account_move_name_sequence/i18n/fr.po
odoo/addons/account_move_name_sequence/i18n/hr.po
odoo/addons/account_move_name_sequence/i18n/it.po
odoo/addons/account_move_name_sequence/i18n/pt_BR.po
odoo/addons/account_move_name_sequence/i18n/sl.po
odoo/addons/account_move_name_sequence/models/__init__.py
odoo/addons/account_move_name_sequence/models/account_journal.py
odoo/addons/account_move_name_sequence/models/account_move.py
odoo/addons/account_move_name_sequence/models/ir_sequence.py
odoo/addons/account_move_name_sequence/readme/CONFIGURE.md
odoo/addons/account_move_name_sequence/readme/CONTRIBUTORS.md
odoo/addons/account_move_name_sequence/readme/DESCRIPTION.md
odoo/addons/account_move_name_sequence/security/ir.model.access.csv
odoo/addons/account_move_name_sequence/static/description/icon.png
odoo/addons/account_move_name_sequence/static/description/index.html
odoo/addons/account_move_name_sequence/tests/__init__.py
odoo/addons/account_move_name_sequence/tests/test_account_incoming_supplier_invoice.py
odoo/addons/account_move_name_sequence/tests/test_account_move_name_seq.py
odoo/addons/account_move_name_sequence/tests/test_account_move_name_seq_hashed_journal.py
odoo/addons/account_move_name_sequence/tests/test_sequence_concurrency.py
odoo/addons/account_move_name_sequence/views/account_journal_views.xml
odoo/addons/account_move_name_sequence/views/account_move_views.xml
odoo_addon_account_move_name_sequence-19.0.1.0.0.2.dist-info/METADATA
odoo_addon_account_move_name_sequence-19.0.1.0.0.2.dist-info/WHEEL
odoo_addon_account_move_name_sequence-19.0.1.0.0.2.dist-info/top_level.txt
odoo_addon_account_move_name_sequence-19.0.1.0.0.2.dist-info/RECORD
