Metadata-Version: 2.1
Name: odoo-addon-account_move_name_sequence
Version: 19.0.1.0.0.2
Requires-Dist: odoo==19.0.*
Summary: Generate journal entry number from sequence
Home-page: https://github.com/OCA/account-financial-tools
License: AGPL-3
Author: Akretion,Vauxoo,Odoo Community Association (OCA)
Author-email: support@odoo-community.org
Classifier: Programming Language :: Python
Classifier: Framework :: Odoo
Classifier: Framework :: Odoo :: 19.0
Classifier: License :: OSI Approved :: GNU Affero General Public License v3
